{"stateCounter":8,"actionCounter":12,"parameterCounter":2,"ePFhost":"macAgent","ePFsuite":"","suitePath":"","path":"","verbosity":31488,"snippetFull":true,"globalActionContainerCoords":{"dx":280,"dy":280,"shapeWidth":220,"shapeHeight":80},"allSnippetsDisabled":false,"runCleanupAfterAbort":false,"allowGlobalActionsInInitialStates":true,"performanceTimings":false,"elements":[{"name":"trueFalseLogic","type":"Root","id":0,"parameters":[{"id":1,"name":"","type":"","initial":"","random":"","ranges":[]}]},{"name":"Exit","type":"State","id":1,"parentId":0,"stateType":"Normal","invisible":true,"sortingType":"Z","parameters":[{"id":0,"name":"","type":"","initial":"","random":"","ranges":[]}]},{"name":"Error","type":"State","id":2,"parentId":0,"stateType":"Exception","invisible":true,"sortingType":"X","parameters":[{"id":0,"name":"","type":"","initial":"","random":"","ranges":[]}]},{"name":"Cleanup","type":"State","id":3,"parentId":0,"stateType":"Cleanup","invisible":true,"sortingType":"Y","parameters":[{"id":0,"name":"","type":"","initial":"","random":"","ranges":[]}]},{"name":"Initial","type":"State","id":4,"parentId":0,"dx":20,"dy":20,"textX":20,"textY":25,"shapeWidth":120,"shapeHeight":100,"stateType":"Start","invisible":false,"sortingType":"A","parameters":[{"id":0,"name":"","type":"","initial":"","random":"","ranges":[]}]},{"name":"login page","type":"State","id":5,"parentId":0,"dx":160,"dy":20,"textX":20,"textY":25,"shapeWidth":320,"shapeHeight":160,"stateType":"Normal","invisible":false,"sortingType":"B","snippets":[{"name":"eggyIcon3_Validate","fullName":"bankingLoginScreen3.script:eggyIcon3_Validate","scriptPath":"bankingLoginScreen3.script:eggyIcon3_Validate","type":"normal","inputs":[{"parameterRef":{"id":2,"name":"credentials","type":"Record","initial":"credentials.csv","random":"Generated unique","ranges":[]},"order":3}]}],"parameters":[{"id":0,"name":"userEntered","type":"True or False","initial":"false","random":"Non-generated","ranges":[]},{"id":1,"name":"pwdEntered","type":"True or False","initial":"false","random":"Non-generated","ranges":[]},{"id":2,"name":"credentials","type":"Record","initial":"credentials.csv","random":"Generated unique","ranges":[]}]},{"name":"Accounts Page","type":"State","id":9,"parentId":0,"dx":560,"dy":60,"textX":20,"textY":25,"shapeWidth":140,"shapeHeight":160,"stateType":"Normal","invisible":false,"sortingType":"B","parameters":[{"id":0,"name":"","type":"","initial":"","random":"","ranges":[]}]},{"name":"payments page","type":"State","id":14,"parentId":0,"dx":760,"dy":80,"textX":20,"textY":25,"shapeWidth":140,"shapeHeight":100,"stateType":"Normal","invisible":false,"sortingType":"B","parameters":[{"id":0,"name":"","type":"","initial":"","random":"","ranges":[]}]},{"name":"transfers page","type":"State","id":15,"parentId":0,"dx":760,"dy":240,"textX":20,"textY":25,"shapeWidth":120,"shapeHeight":100,"stateType":"Normal","invisible":false,"sortingType":"B","parameters":[{"id":0,"name":"","type":"","initial":"","random":"","ranges":[]}]},{"name":"username","type":"Action","id":6,"parentId":5,"dx":20,"dy":40,"textX":15,"textY":22,"shapeWidth":80,"shapeHeight":40,"actionType":"Normal","sortingType":"C","snippets":[{"name":"uname3_EnterText","fullName":"bankingLoginScreen3.script:uname3_EnterText","scriptPath":"bankingLoginScreen3.script:uname3_EnterText","type":"normal","inputs":[{"parameterRef":{"id":2,"name":"credentials","type":"Record","initial":"credentials.csv","random":"Generated unique","ranges":[]},"order":3}]}],"parameters":[{"id":0,"name":"","type":"","initial":"","random":"","ranges":[]}],"preconditions":[],"setGenerate":[{"parameterName":"userEntered","setGen":"set","value":"true"}],"callLimit":0,"weight":100},{"name":"password","type":"Action","id":7,"parentId":5,"dx":20,"dy":100,"textX":15,"textY":22,"shapeWidth":80,"shapeHeight":40,"actionType":"Normal","sortingType":"C","parameters":[{"id":0,"name":"","type":"","initial":"","random":"","ranges":[]}],"setGenerate":[{"parameterName":"pwdEntered","setGen":"set","value":"true"}],"callLimit":0,"weight":100},{"name":"login","type":"Action","id":8,"parentId":5,"dx":220,"dy":40,"textX":15,"textY":22,"shapeWidth":80,"shapeHeight":40,"actionType":"Normal","sortingType":"C","parameters":[{"id":0,"name":"","type":"","initial":"","random":"","ranges":[]}],"preconditions":[{"parameterName":"userEntered","condition":"==","value":"true"},{"parameterName":"pwdEntered","condition":"==","value":"true"}],"setGenerate":[{"parameterName":"userEntered","setGen":"set","value":"false"},{"parameterName":"pwdEntered","setGen":"set","value":"false"}],"connectedStates":[{"stateRef":9}],"checks":[{"parameterName":"pwdEntered","condition":"==","value":"false","message":"login worked"}],"callLimit":0,"weight":100,"tags":[{"name":"Developer","value":"Jacob","id":1}]},{"name":"launch","type":"Action","id":11,"parentId":4,"dx":20,"dy":40,"textX":15,"textY":22,"shapeWidth":80,"shapeHeight":40,"actionType":"Normal","sortingType":"C","snippets":[{"name":"launchIt","fullName":"launchIt.script","scriptPath":"launchIt.script","type":"normal"}],"parameters":[{"id":0,"name":"","type":"","initial":"","random":"","ranges":[]}],"connectedStates":[{"stateRef":5}],"callLimit":0,"weight":100},{"name":"Payments","type":"Action","id":12,"parentId":9,"dx":20,"dy":40,"textX":15,"textY":22,"shapeWidth":80,"shapeHeight":40,"actionType":"Normal","sortingType":"C","parameters":[{"id":0,"name":"","type":"","initial":"","random":"","ranges":[]}],"connectedStates":[{"stateRef":14}],"callLimit":0,"weight":100},{"name":"transfers","type":"Action","id":13,"parentId":9,"dx":20,"dy":100,"textX":15,"textY":22,"shapeWidth":80,"shapeHeight":40,"actionType":"Normal","sortingType":"C","parameters":[{"id":0,"name":"","type":"","initial":"","random":"","ranges":[]}],"connectedStates":[{"stateRef":15}],"callLimit":0,"weight":100},{"name":"cancel","type":"Action","id":16,"parentId":14,"dx":20,"dy":40,"textX":15,"textY":22,"shapeWidth":80,"shapeHeight":40,"actionType":"Previous","sortingType":"C","parameters":[{"id":0,"name":"","type":"","initial":"","random":"","ranges":[]}],"connectedStates":[],"callLimit":0,"weight":100},{"name":"cancel","type":"Action","id":18,"parentId":15,"dx":20,"dy":40,"textX":15,"textY":22,"shapeWidth":80,"shapeHeight":40,"actionType":"Previous","sortingType":"C","parameters":[{"id":0,"name":"","type":"","initial":"","random":"","ranges":[]}],"connectedStates":[],"callLimit":0,"weight":100},{"name":"back to home","type":"Action","id":19,"parentId":0,"dx":20,"dy":20,"textX":15,"textY":22,"shapeWidth":93,"shapeHeight":40,"actionType":"Normal","sortingType":"C","parameters":[{"id":0,"name":"","type":"","initial":"","random":"","ranges":[]}],"connectedStates":[{"stateRef":5}],"callLimit":0,"weight":100},{"name":"quit","type":"Action","id":20,"parentId":0,"dx":120,"dy":20,"textX":15,"textY":22,"shapeWidth":80,"shapeHeight":40,"actionType":"Normal","sortingType":"C","parameters":[{"id":0,"name":"","type":"","initial":"","random":"","ranges":[]}],"connectedStates":[{"stateRef":1}],"callLimit":0,"weight":100}],"testcases":[],"performanceTests":[],"tags":[{"name":"Developer","values":"Anne,Jacob,Jill","id":1},{"name":"Version","values":"14,15,16","id":2},{"name":"Technology","values":"HTML4, HTML5","id":3}],"version":"4.0.1"}